LICENSE.txt
MANIFEST.in
README.md
setup.py
django_masked_forms.egg-info/PKG-INFO
django_masked_forms.egg-info/SOURCES.txt
django_masked_forms.egg-info/dependency_links.txt
django_masked_forms.egg-info/not-zip-safe
django_masked_forms.egg-info/top_level.txt
masked_forms/__init__.py
masked_forms/forms.py
masked_forms/models.py
masked_forms/tests.py
masked_forms/views.py
masked_forms/media/.DS_Store
masked_forms/media/masked_forms/.DS_Store
masked_forms/media/masked_forms/js/jquery.maskedinput.js
masked_forms/media/masked_forms/js/masked_forms.js