Metadata-Version: 1.0
Name: django-masked-forms
Version: 0.0.1
Summary: django masked forms
Home-page: https://github.com/comogo/django-masked-forms
Author: Mateus Lorandi dos Santos
Author-email: mcomogo@gmail.com
License: MIT
Keywords: jQuery,django,mask,form fields
Platform: UNKNOWN
Classifier: Programming Language :: Python
Classifier: Topic :: Software Development :: Libraries :: Python Modules
Classifier: Framework :: Django
Classifier: Environment :: Web Environment
